{"团子硬核露营":{"type":"image","container":[{"text":"tuan-zi-ying-he-lu-ying_拜拜","icon":"<img src='https://emoticons.assets.hzchu.top/emoticons/tuan-zi-ying-he-lu-ying/5.webp'>"},{"text":"tuan-zi-ying-he-lu-ying_背包","icon":"<img src='https://emoticons.assets.hzchu.top/emoticons/tuan-zi-ying-he-lu-ying/12.webp'>"},{"text":"tuan-zi-ying-he-lu-ying_加油","icon":"<img src='https://emoticons.assets.hzchu.top/emoticons/tuan-zi-ying-he-lu-ying/1.webp'>"},{"text":"tuan-zi-ying-he-lu-ying_杯子","icon":"<img src='https://emoticons.assets.hzchu.top/emoticons/tuan-zi-ying-he-lu-ying/13.webp'>"},{"text":"tuan-zi-ying-he-lu-ying_树","icon":"<img src='https://emoticons.assets.hzchu.top/emoticons/tuan-zi-ying-he-lu-ying/15.webp'>"},{"text":"tuan-zi-ying-he-lu-ying_火","icon":"<img src='https://emoticons.assets.hzchu.top/emoticons/tuan-zi-ying-he-lu-ying/10.webp'>"},{"text":"tuan-zi-ying-he-lu-ying_钓鱼上","icon":"<img src='https://emoticons.assets.hzchu.top/emoticons/tuan-zi-ying-he-lu-ying/9.webp'>"},{"text":"tuan-zi-ying-he-lu-ying_炉子","icon":"<img src='https://emoticons.assets.hzchu.top/emoticons/tuan-zi-ying-he-lu-ying/6.webp'>"},{"text":"tuan-zi-ying-he-lu-ying_露营右","icon":"<img src='https://emoticons.assets.hzchu.top/emoticons/tuan-zi-ying-he-lu-ying/8.webp'>"},{"text":"tuan-zi-ying-he-lu-ying_闹钟","icon":"<img src='https://emoticons.assets.hzchu.top/emoticons/tuan-zi-ying-he-lu-ying/11.webp'>"},{"text":"tuan-zi-ying-he-lu-ying_露营左","icon":"<img src='https://emoticons.assets.hzchu.top/emoticons/tuan-zi-ying-he-lu-ying/7.webp'>"},{"text":"tuan-zi-ying-he-lu-ying_蹲蹲","icon":"<img src='https://emoticons.assets.hzchu.top/emoticons/tuan-zi-ying-he-lu-ying/4.webp'>"},{"text":"tuan-zi-ying-he-lu-ying_喝水","icon":"<img src='https://emoticons.assets.hzchu.top/emoticons/tuan-zi-ying-he-lu-ying/2.webp'>"},{"text":"tuan-zi-ying-he-lu-ying_钓鱼下","icon":"<img src='https://emoticons.assets.hzchu.top/emoticons/tuan-zi-ying-he-lu-ying/14.webp'>"},{"text":"tuan-zi-ying-he-lu-ying_开心","icon":"<img src='https://emoticons.assets.hzchu.top/emoticons/tuan-zi-ying-he-lu-ying/3.webp'>"}]}}