{
    "name": "猫你太美",
    "type": "image",
    "items": [
        {
            "key": "mao-ni-tai-mei_哈哈",
            "val": "https://emoticons.hzchu.top/emoticons/mao-ni-tai-mei/10.png"
        },
        {
            "key": "mao-ni-tai-mei_比心",
            "val": "https://emoticons.hzchu.top/emoticons/mao-ni-tai-mei/8.png"
        },
        {
            "key": "mao-ni-tai-mei_欢喜",
            "val": "https://emoticons.hzchu.top/emoticons/mao-ni-tai-mei/3.png"
        },
        {
            "key": "mao-ni-tai-mei_溜",
            "val": "https://emoticons.hzchu.top/emoticons/mao-ni-tai-mei/23.png"
        },
        {
            "key": "mao-ni-tai-mei_吃瓜",
            "val": "https://emoticons.hzchu.top/emoticons/mao-ni-tai-mei/22.png"
        },
        {
            "key": "mao-ni-tai-mei_哭",
            "val": "https://emoticons.hzchu.top/emoticons/mao-ni-tai-mei/25.png"
        },
        {
            "key": "mao-ni-tai-mei_不",
            "val": "https://emoticons.hzchu.top/emoticons/mao-ni-tai-mei/1.png"
        },
        {
            "key": "mao-ni-tai-mei_哼",
            "val": "https://emoticons.hzchu.top/emoticons/mao-ni-tai-mei/2.png"
        },
        {
            "key": "mao-ni-tai-mei_双币",
            "val": "https://emoticons.hzchu.top/emoticons/mao-ni-tai-mei/9.png"
        },
        {
            "key": "mao-ni-tai-mei_咦",
            "val": "https://emoticons.hzchu.top/emoticons/mao-ni-tai-mei/15.png"
        },
        {
            "key": "mao-ni-tai-mei_yue",
            "val": "https://emoticons.hzchu.top/emoticons/mao-ni-tai-mei/18.png"
        },
        {
            "key": "mao-ni-tai-mei_老猫看手机",
            "val": "https://emoticons.hzchu.top/emoticons/mao-ni-tai-mei/4.png"
        },
        {
            "key": "mao-ni-tai-mei_盯",
            "val": "https://emoticons.hzchu.top/emoticons/mao-ni-tai-mei/24.png"
        },
        {
            "key": "mao-ni-tai-mei_嘻嘻",
            "val": "https://emoticons.hzchu.top/emoticons/mao-ni-tai-mei/21.png"
        },
        {
            "key": "mao-ni-tai-mei_鸽子",
            "val": "https://emoticons.hzchu.top/emoticons/mao-ni-tai-mei/14.png"
        },
        {
            "key": "mao-ni-tai-mei_抱拳",
            "val": "https://emoticons.hzchu.top/emoticons/mao-ni-tai-mei/11.png"
        },
        {
            "key": "mao-ni-tai-mei_委屈",
            "val": "https://emoticons.hzchu.top/emoticons/mao-ni-tai-mei/19.png"
        },
        {
            "key": "mao-ni-tai-mei_困",
            "val": "https://emoticons.hzchu.top/emoticons/mao-ni-tai-mei/17.png"
        },
        {
            "key": "mao-ni-tai-mei_ok",
            "val": "https://emoticons.hzchu.top/emoticons/mao-ni-tai-mei/16.png"
        },
        {
            "key": "mao-ni-tai-mei_Zzzz",
            "val": "https://emoticons.hzchu.top/emoticons/mao-ni-tai-mei/20.png"
        },
        {
            "key": "mao-ni-tai-mei_生气",
            "val": "https://emoticons.hzchu.top/emoticons/mao-ni-tai-mei/7.png"
        },
        {
            "key": "mao-ni-tai-mei_无语",
            "val": "https://emoticons.hzchu.top/emoticons/mao-ni-tai-mei/6.png"
        },
        {
            "key": "mao-ni-tai-mei_打call",
            "val": "https://emoticons.hzchu.top/emoticons/mao-ni-tai-mei/13.png"
        },
        {
            "key": "mao-ni-tai-mei_赞",
            "val": "https://emoticons.hzchu.top/emoticons/mao-ni-tai-mei/5.png"
        },
        {
            "key": "mao-ni-tai-mei_噗",
            "val": "https://emoticons.hzchu.top/emoticons/mao-ni-tai-mei/12.png"
        }
    ]
}